flask_warehouse/__init__.py
flask_warehouse/flask_warehouse.py
flask_warehouse/backends/__init__.py
flask_warehouse/backends/file.py
flask_warehouse/backends/s3.py
flask_warehouse/backends/service.py
flask_warehouse-0.1.12.dist-info/AUTHORS.rst
flask_warehouse-0.1.12.dist-info/LICENSE
flask_warehouse-0.1.12.dist-info/METADATA
flask_warehouse-0.1.12.dist-info/WHEEL
flask_warehouse-0.1.12.dist-info/top_level.txt
flask_warehouse-0.1.12.dist-info/RECORD
