Metadata-Version: 2.1
Name: flask-warehouse
Version: 0.1.12
Summary: A clean abstraction over cloud file storage platforms like S3, Alicloud, or Heroku.
Home-page: https://github.com/augustjd/flask-warehouse
Author: Joshua Augustin
Author-email: augustinspring@gmail.com
License: MIT license
Keywords: flask_warehouse
Platform: UNKNOWN
Classifier: Development Status :: 2 - Pre-Alpha
Classifier: Intended Audience :: Developers
Classifier: License :: OSI Approved :: MIT License
Classifier: Natural Language :: English
Classifier: Programming Language :: Python :: 3
Classifier: Programming Language :: Python :: 3.3
Classifier: Programming Language :: Python :: 3.4
Classifier: Programming Language :: Python :: 3.5
Requires-Dist: Flask (>=1.0)
